pyxp/__init__.py
pyxp/pyxp.py
pyxp-1.0.0.dist-info/DESCRIPTION.rst
pyxp-1.0.0.dist-info/METADATA
pyxp-1.0.0.dist-info/metadata.json
pyxp-1.0.0.dist-info/RECORD
pyxp-1.0.0.dist-info/top_level.txt
pyxp-1.0.0.dist-info/WHEEL
