Metadata-Version: 2.0
Name: pyxp
Version: 1.0.0
Summary: A library for construct arithmetic expression in python, which could be serialize to and deserialize from string
Home-page: https://github.com/Xorcerer/pyxp
Author: Logan Zhou
Author-email: xorcererzc@gmail.com
License: MIT
Keywords: math arithmetic expression AST abstract syntax tree serialization
Platform: UNKNOWN
Classifier: Development Status :: 4 - Beta
Classifier: Intended Audience :: Developers
Classifier: Topic :: Software Development :: Libraries
Classifier: License :: OSI Approved :: MIT License
Classifier: Programming Language :: Python :: 2
Classifier: Programming Language :: Python :: 2.6
Classifier: Programming Language :: Python :: 2.7
Classifier: Programming Language :: Python :: 3
Classifier: Programming Language :: Python :: 3.2
Classifier: Programming Language :: Python :: 3.3
Classifier: Programming Language :: Python :: 3.4
